webscrapbook/__init__.py
webscrapbook/__main__.py
webscrapbook/app.py
webscrapbook/cli.py
webscrapbook/locales.py
webscrapbook/server.py
webscrapbook/_polyfill/__init__.py
webscrapbook/_polyfill/argparse.py
webscrapbook/_polyfill/mimetypes.py
webscrapbook/_polyfill/zipfile.py
webscrapbook/resources/app.py
webscrapbook/resources/config.ini
webscrapbook/resources/config.md
webscrapbook/resources/mimetypes.md
webscrapbook/resources/serve.py
webscrapbook/resources/themes.md
webscrapbook/scrapbook/__init__.py
webscrapbook/scrapbook/book.py
webscrapbook/scrapbook/cache.py
webscrapbook/scrapbook/check.py
webscrapbook/scrapbook/exporter.py
webscrapbook/scrapbook/exporter1.py
webscrapbook/scrapbook/host.py
webscrapbook/scrapbook/importer.py
webscrapbook/scrapbook/importer1.py
webscrapbook/scrapbook/indexer.py
webscrapbook/scrapbook/search.py
webscrapbook/scrapbook/util.py
webscrapbook/scrapbook/convert/__init__.py
webscrapbook/scrapbook/convert/file2wsb.py
webscrapbook/scrapbook/convert/items.py
webscrapbook/scrapbook/convert/migrate.py
webscrapbook/scrapbook/convert/sb2wsb.py
webscrapbook/scrapbook/convert/wsb2file.py
webscrapbook/scrapbook/convert/wsb2sb.py
webscrapbook/themes/default/locales/ar/messages.py
webscrapbook/themes/default/locales/en/messages.py
webscrapbook/themes/default/locales/es/messages.py
webscrapbook/themes/default/locales/fa/messages.py
webscrapbook/themes/default/locales/he/messages.py
webscrapbook/themes/default/locales/zh/messages.py
webscrapbook/themes/default/locales/zh_cn/messages.py
webscrapbook/themes/default/static/collapse.png
webscrapbook/themes/default/static/comment.png
webscrapbook/themes/default/static/common.css
webscrapbook/themes/default/static/common.js
webscrapbook/themes/default/static/edit.css
webscrapbook/themes/default/static/edit.js
webscrapbook/themes/default/static/editx.js
webscrapbook/themes/default/static/expand.png
webscrapbook/themes/default/static/external.png
webscrapbook/themes/default/static/fclose.png
webscrapbook-2.8.0.dist-info/licenses/LICENSE.txt
webscrapbook-2.8.0.dist-info/METADATA
webscrapbook-2.8.0.dist-info/WHEEL
webscrapbook-2.8.0.dist-info/entry_points.txt
webscrapbook-2.8.0.dist-info/top_level.txt
webscrapbook-2.8.0.dist-info/RECORD
