Metadata-Version: 2.4
Name: webscrapbook
Version: 2.8.0
Summary: A backend toolkit for management of WebScrapBook collection.
Author-email: Danny Lin <danny0838@gmail.com>
License: MIT
Project-URL: Homepage, https://github.com/danny0838/PyWebScrapBook
Classifier: Development Status :: 5 - Production/Stable
Classifier: Operating System :: OS Independent
Classifier: Programming Language :: Python :: 3
Classifier: Programming Language :: Python :: 3 :: Only
Classifier: Programming Language :: Python :: 3.8
Classifier: Programming Language :: Python :: 3.9
Classifier: Programming Language :: Python :: 3.10
Classifier: Programming Language :: Python :: 3.11
Classifier: Programming Language :: Python :: 3.12
Classifier: Programming Language :: Python :: 3.13
Classifier: Programming Language :: Python :: 3.14
Classifier: Topic :: Internet :: WWW/HTTP :: Dynamic Content :: Content Management System
Classifier: Topic :: Internet :: WWW/HTTP :: Indexing/Search
Classifier: Topic :: Internet :: WWW/HTTP :: HTTP Servers
Classifier: Topic :: Internet :: WWW/HTTP :: WSGI :: Server
Classifier: Topic :: Internet :: WWW/HTTP :: WSGI :: Application
Classifier: Intended Audience :: End Users/Desktop
Classifier: Intended Audience :: Science/Research
Requires-Python: ~=3.8
License-File: LICENSE.txt
Requires-Dist: flask>=2.0.0
Requires-Dist: werkzeug>=2.0.1
Requires-Dist: jinja2>=2.10.1
Requires-Dist: lxml>=4.0
Requires-Dist: commonmark>=0.8
Provides-Extra: adhoc-ssl
Requires-Dist: cryptography; extra == "adhoc-ssl"
Dynamic: license
Dynamic: license-file
